blart/__init__.py
blart/__init__.pyi
blart/_blart.cpython-314-darwin.so
blart/py.typed
blart_py-0.1.2.dist-info/METADATA
blart_py-0.1.2.dist-info/WHEEL
blart_py-0.1.2.dist-info/licenses/LICENSE
blart_py-0.1.2.dist-info/RECORD
