Metadata-Version: 2.4
Name: blart-py
Version: 0.1.2
Classifier: Development Status :: 4 - Beta
Classifier: Intended Audience :: Developers
Classifier: License :: OSI Approved :: MIT License
Classifier: Programming Language :: Rust
Classifier: Programming Language :: Python :: Implementation :: CPython
Classifier: Programming Language :: Python :: 3
Classifier: Programming Language :: Python :: 3.8
Classifier: Programming Language :: Python :: 3.9
Classifier: Programming Language :: Python :: 3.10
Classifier: Programming Language :: Python :: 3.11
Classifier: Programming Language :: Python :: 3.12
Classifier: Topic :: Software Development :: Libraries :: Python Modules
Classifier: Topic :: Scientific/Engineering
Classifier: Typing :: Typed
License-File: LICENSE
Summary: High-performance adaptive radix tree (ART) for Python with prefix queries and fuzzy search
Keywords: tree,radix,trie,prefix,fuzzy-search,data-structure
Author: Axel Vanraes
Maintainer: Axel Vanraes
Requires-Python: >=3.8
Project-URL: Homepage, https://github.com/axelv/blart-py
Project-URL: Documentation, https://github.com/axelv/blart-py#readme
Project-URL: Repository, https://github.com/axelv/blart-py
Project-URL: Issues, https://github.com/axelv/blart-py/issues
Project-URL: Changelog, https://github.com/axelv/blart-py/blob/main/CHANGELOG.md
